odoo/addons/shipment_advice_planner/README.rst
odoo/addons/shipment_advice_planner/__init__.py
odoo/addons/shipment_advice_planner/__manifest__.py
odoo/addons/shipment_advice_planner/i18n/es.po
odoo/addons/shipment_advice_planner/i18n/it.po
odoo/addons/shipment_advice_planner/i18n/shipment_advice_planner.pot
odoo/addons/shipment_advice_planner/models/__init__.py
odoo/addons/shipment_advice_planner/models/stock_picking.py
odoo/addons/shipment_advice_planner/readme/CONTRIBUTORS.md
odoo/addons/shipment_advice_planner/readme/DESCRIPTION.md
odoo/addons/shipment_advice_planner/readme/USAGE.md
odoo/addons/shipment_advice_planner/security/shipment_advice_planner.xml
odoo/addons/shipment_advice_planner/static/description/icon.png
odoo/addons/shipment_advice_planner/static/description/index.html
odoo/addons/shipment_advice_planner/tests/__init__.py
odoo/addons/shipment_advice_planner/tests/common.py
odoo/addons/shipment_advice_planner/tests/test_picking_can_be_planned.py
odoo/addons/shipment_advice_planner/tests/test_shipment_advice_planner.py
odoo/addons/shipment_advice_planner/wizards/__init__.py
odoo/addons/shipment_advice_planner/wizards/shipment_advice_planner.py
odoo/addons/shipment_advice_planner/wizards/shipment_advice_planner.xml
odoo_addon_shipment_advice_planner-18.0.1.1.0.dist-info/METADATA
odoo_addon_shipment_advice_planner-18.0.1.1.0.dist-info/WHEEL
odoo_addon_shipment_advice_planner-18.0.1.1.0.dist-info/top_level.txt
odoo_addon_shipment_advice_planner-18.0.1.1.0.dist-info/RECORD
