Metadata-Version: 2.1
Name: odoo-addon-shipment_advice_planner
Version: 18.0.1.1.0
Requires-Python: >=3.10
Requires-Dist: odoo-addon-shipment_advice==18.0.*
Requires-Dist: odoo==18.0.*
Summary: This module is used to plan ready transfers in shipment advices.
Home-page: https://github.com/OCA/stock-logistics-transport
License: AGPL-3
Author: ACSONE SA/NV,BCIM,Odoo Community Association (OCA)
Author-email: support@odoo-community.org
Classifier: Programming Language :: Python
Classifier: Framework :: Odoo
Classifier: Framework :: Odoo :: 18.0
Classifier: License :: OSI Approved :: GNU Affero General Public License v3
